doccraft/__init__.py
doccraft/cli.py
doccraft/benchmarking/__init__.py
doccraft/benchmarking/accuracy_benchmarker.py
doccraft/benchmarking/base_benchmarker.py
doccraft/benchmarking/docvqa_benchmarker.py
doccraft/benchmarking/evaluate.py
doccraft/benchmarking/performance_benchmarker.py
doccraft/parsers/__init__.py
doccraft/parsers/base_ai_parser.py
doccraft/parsers/base_parser.py
doccraft/parsers/deepseek_vl_parser.py
doccraft/parsers/layoutlmv3_parser.py
doccraft/parsers/paddle_ocr_parser.py
doccraft/parsers/pdf_parser.py
doccraft/parsers/pdfplumber_parser.py
doccraft/parsers/qwen_vl_parser.py
doccraft/parsers/tesseract_parser.py
doccraft/postprocessing/__init__.py
doccraft/postprocessing/base_postprocessor.py
doccraft/postprocessing/table_postprocessor.py
doccraft/postprocessing/text_postprocessor.py
doccraft/preprocessing/__init__.py
doccraft/preprocessing/base_preprocessor.py
doccraft/preprocessing/image_preprocessor.py
doccraft/preprocessing/pdf_preprocessor.py
doccraft_toolkit-0.1.2.dist-info/licenses/LICENSE
doccraft_toolkit-0.1.2.dist-info/METADATA
doccraft_toolkit-0.1.2.dist-info/WHEEL
doccraft_toolkit-0.1.2.dist-info/entry_points.txt
doccraft_toolkit-0.1.2.dist-info/top_level.txt
doccraft_toolkit-0.1.2.dist-info/RECORD
