Metadata-Version: 2.4
Name: doccraft-toolkit
Version: 0.1.2
Summary: A comprehensive document processing and question-answering toolkit
Home-page: https://github.com/WuSimon/DocCraft
Author: Simon Wu
Author-email: simon.wu@rwth-aachen.de
Classifier: Development Status :: 3 - Alpha
Classifier: Intended Audience :: Developers
Classifier: Intended Audience :: Science/Research
Classifier: License :: OSI Approved :: MIT License
Classifier: Operating System :: OS Independent
Classifier: Programming Language :: Python :: 3
Classifier: Programming Language :: Python :: 3.8
Classifier: Programming Language :: Python :: 3.9
Classifier: Programming Language :: Python :: 3.10
Classifier: Programming Language :: Python :: 3.11
Classifier: Programming Language :: Python :: 3.12
Classifier: Topic :: Scientific/Engineering :: Artificial Intelligence
Classifier: Topic :: Software Development :: Libraries :: Python Modules
Requires-Python: >=3.8
License-File: LICENSE
Requires-Dist: numpy>=1.21.0
Requires-Dist: Pillow>=8.0.0
Requires-Dist: PyMuPDF>=1.18.0
Requires-Dist: pdfplumber>=0.7.0
Requires-Dist: pytesseract>=0.3.8
Requires-Dist: opencv-python>=4.5.0
Requires-Dist: scipy>=1.7.0
Requires-Dist: pandas>=1.3.0
Requires-Dist: openpyxl>=3.0.0
Requires-Dist: psutil>=5.8.0
Requires-Dist: paddlepaddle>=2.4.0
Requires-Dist: paddleocr>=2.6.0
Provides-Extra: ai
Requires-Dist: transformers>=4.30.0; extra == "ai"
Requires-Dist: torch>=2.0.0; extra == "ai"
Requires-Dist: torchvision>=0.15.0; extra == "ai"
Requires-Dist: matplotlib>=3.3.0; extra == "ai"
Requires-Dist: transformers_stream_generator>=0.0.5; extra == "ai"
Requires-Dist: num2words>=0.5.10; extra == "ai"
Requires-Dist: inflect>=6.0.0; extra == "ai"
Provides-Extra: dev
Requires-Dist: pytest>=6.0.0; extra == "dev"
Requires-Dist: pytest-cov>=2.12.0; extra == "dev"
Requires-Dist: black>=22.3.0; extra == "dev"
Requires-Dist: flake8>=4.0.1; extra == "dev"
Requires-Dist: mypy>=0.910; extra == "dev"
Requires-Dist: python-Levenshtein>=0.12.2; extra == "dev"
Requires-Dist: munkres>=1.1.4; extra == "dev"
Requires-Dist: num2words>=0.5.10; extra == "dev"
Requires-Dist: inflect>=6.0.0; extra == "dev"
Provides-Extra: all
Requires-Dist: transformers>=4.30.0; extra == "all"
Requires-Dist: torch>=2.0.0; extra == "all"
Requires-Dist: torchvision>=0.15.0; extra == "all"
Requires-Dist: matplotlib>=3.3.0; extra == "all"
Requires-Dist: transformers_stream_generator>=0.0.5; extra == "all"
Requires-Dist: pytest>=6.0.0; extra == "all"
Requires-Dist: pytest-cov>=2.12.0; extra == "all"
Requires-Dist: black>=22.3.0; extra == "all"
Requires-Dist: flake8>=4.0.1; extra == "all"
Requires-Dist: mypy>=0.910; extra == "all"
Requires-Dist: python-Levenshtein>=0.12.2; extra == "all"
Requires-Dist: munkres>=1.1.4; extra == "all"
Requires-Dist: num2words>=0.5.10; extra == "all"
Requires-Dist: inflect>=6.0.0; extra == "all"
Dynamic: author
Dynamic: author-email
Dynamic: classifier
Dynamic: description
Dynamic: description-content-type
Dynamic: home-page
Dynamic: license-file
Dynamic: provides-extra
Dynamic: requires-dist
Dynamic: requires-python
Dynamic: summary
